{
  "date": "2026-07-29",
  "time_kst": "08:30",
  "topic": "무이네",
  "text": "베트남에서 【사막】 보고 싶으면 무이네임. 악뮤 '소문의 낙원' 뮤비 촬영지가 몽골이 아니라 여기임.\n\n- 호치민에서 차로 3~4시간. 당일치기도 되는데 일출 보려면 1박이 국룰임\n- 코스는 화이트샌듄(일출)+레드샌듄(일몰)+요정의샘 조합. 지프 타고 도는 게 기본임\n- 지프투어는 숙소 프런트에서 잡으면 1인 2~3만원대부터 있음. 한인 플랫폼 단독투어는 비싼 대신 픽업·한국어가 편함\n- 화이트샌듄 입장료 15,000동(800원대). 요정의샘은 붉은 협곡 사이 개울을 맨발로 걷는 코스임 (기준시점: 2026.7)\n- 무조건 새벽 일출팀 추천. 해 뜨고 나면 모래가 진짜 뜨거움\n\n호치민→무이네는 슬리핑버스 15만동대로 감. 사막+바다+어촌마을을 하루에 다 보는 동네는 베트남에서 여기뿐임.",
  "sources": "📍출처·소재 (수집 2026-07-12)\nhttps://www.threads.com/@bomulchang_go/post/DW_PW22kpdH — [Threads/현지 투어사] 악뮤 '소문의 낙원' 촬영지=무이네, 호치민서 3~4시간, 선라이즈/선셋 패키지 구성\nhttps://giantarchive.com/무이네-여행-경비-2026-숙소-물가-계산기-후기-총정리/ — 2026 무이네 경비 가이드: 숙소 프런트 지프투어 1인 2~3만원, 화이트샌듄 입장료 15,000동, 요정의샘 코스\nhttps://experiences.myrealtrip.com/products/3446500 — 마이리얼트립 무이네 지프 선셋 단독투어(한인 플랫폼 상품 예시)\n⚠️ 정책·수치 변동 가능·공식 확인",
  "card": {
    "kicker": "베트남 히든플레이스",
    "headline": "베트남에 *사막* 있음\n무이네 지프투어",
    "body": "화이트샌듄 일출부터 요정의샘까지, 호치민에서 3~4시간",
    "tag": "#무이네",
    "photoQuery": "mui ne white sand dunes jeep sunrise vietnam"
  }
}