{
  "date": "2026-07-07",
  "time_kst": "21:00",
  "topic": "카메라 앵글 — 높이가 제품 인상을 정한다",
  "text": "같은 제품, 같은 조명인데 사진 느낌이 다르다? 열에 아홉은 【카메라 높이】 차이야.\n\n✔️ 아이레벨(눈높이): 매대에서 보는 그 시선. 왜곡 없고 정직해서 상세페이지 기본컷\n✔️ 하이앵글(위에서): 구성·내용물이 한눈에 — 세트 상품·푸드에 강해. 대신 높이감은 죽어\n✔️ 로우앵글(살짝 아래서): 제품이 우뚝 서 보여 '주인공' 분위기. 향수·주류 메인컷이 이 각이야\n\n스튜디오에서도 한 번에 안 찍어. 카메라를 몇 cm씩 올렸다 내렸다 하면서 제품 어깨선이 제일 사는 지점을 찾는 거야.\n\n장비 탓하기 전에 삼각대 높이부터 바꿔봐. 폰카도 각이 바뀌면 제품이 달라 보인다.",
  "sources": "📍출처·소재 (수집 2026-07-03)\nhttps://www.slrlounge.com — 제품 촬영 카메라 앵글(아이레벨/하이/로우)별 인상 차이 참고\nhttps://petapixel.com — 커머스 제품컷 구도·앵글 기본기 참고\n⚠️ 제품군별 최적 앵글 상이",
  "card": {
    "kicker": "제품 촬영 실전",
    "headline": "조명 말고\n*카메라 높이*를 바꿔봐",
    "body": "아이레벨·하이앵글·로우앵글 — 각이 인상을 정한다",
    "tag": "#제품사진",
    "photoQuery": "product photography studio camera tripod setup"
  }
}